MANIFEST.in
README.rst
setup.py
pykss/__init__.py
pykss/comment.py
pykss/exceptions.py
pykss/modifier.py
pykss/parser.py
pykss/section.py
pykss.egg-info/PKG-INFO
pykss.egg-info/SOURCES.txt
pykss.egg-info/dependency_links.txt
pykss.egg-info/not-zip-safe
pykss.egg-info/requires.txt
pykss.egg-info/top_level.txt
pykss/contrib/__init__.py
pykss/contrib/django/__init__.py
pykss/contrib/django/models.py
pykss/contrib/django/views.py
pykss/contrib/django/static/pykss/js/kss.js
pykss/contrib/django/templates/pykss/styleguideblock.html
pykss/contrib/django/templatetags/__init__.py
pykss/contrib/django/templatetags/pykss.py
tests/test_contrib/__init__.py
tests/test_contrib/test_django/__init__.py
tests/test_contrib/test_django/test_views.py
tests/test_contrib/test_django/test_templatetags/__init__.py
tests/test_contrib/test_django/test_templatetags/test_pykss.py