Metadata-Version: 1.0
Name: pykss
Version: 0.4
Summary: Python implementation of KSS
Home-page: https://github.com/seanbrant/pykss
Author: Sean Brant
Author-email: brant.sean@gmail.com
License: BSD
Platform: UNKNOWN
Classifier: Development Status :: 4 - Beta
Classifier: Environment :: Web Environment
Classifier: Intended Audience :: Developers
Classifier: License :: OSI Approved :: BSD License
Classifier: Operating System :: OS Independent
Classifier: Programming Language :: Python
